{"cell_bit":{"aperture":32,"arch":65536,"block":1,"corridor":4,"door":131072,"label":4278190080,"locked":262144,"nothing":0,"perimeter":16,"portcullis":2097152,"room":2,"room_id":65472,"secret":1048576,"stair_down":4194304,"stair_up":8388608,"trapped":524288},"cells":[[0,0,0,0,0,0,0,0,0,0,0,0,0,0,0,0,0,0,0,0,0,0,0,0,0,0,0,0,0,0,0],[0,0,0,0,0,0,0,0,0,0,0,0,0,0,0,0,0,0,0,0,0,0,0,0,0,0,0,0,0,0,0],[0,0,0,0,0,0,0,0,0,0,0,0,0,0,0,0,0,0,0,0,0,0,0,0,0,0,0,0,0,0,0],[0,0,0,0,0,0,0,0,0,0,0,0,0,0,0,0,0,0,0,0,0,0,0,0,0,0,0,0,0,0,0],[0,0,0,0,0,0,0,0,0,0,0,0,0,0,0,0,0,0,0,0,0,0,0,0,0,0,0,0,0,0,0],[0,0,0,0,0,4,0,4,4,4,0,4,4,4,4,4,4,4,4,4,4,4,4,4,4,4,0,0,0,0,0],[0,0,0,0,0,4,0,4,0,4,0,4,0,4,0,0,0,0,0,0,0,0,0,0,0,4,0,0,0,0,0],[0,0,0,0,0,4,0,4,0,4,0,4,0,4,0,8388612,4,4,4,4,4,4,4,4,4,4,0,0,0,0,0],[0,0,0,0,0,4,0,4,0,4,0,0,0,4,16,16,16,65540,16,16,16,16,16,16,16,16,16,0,0,0,0],[0,0,0,0,0,4,4,4,0,4,4,4,4,4,16,66,66,66,66,66,66,66,66,66,66,66,16,0,0,0,0],[0,0,0,0,16,16,16,16,16,16,16,16,16,0,16,66,66,66,66,66,66,66,66,66,66,66,16,0,0,0,0],[0,0,0,0,16,130,130,130,130,130,130,130,131076,4,16,66,66,66,66,66,66,66,66,66,66,66,16,0,0,0,0],[0,0,0,0,16,130,130,130,130,130,130,130,16,4,16,66,66,66,66,66,66,66,66,66,66,66,16,0,0,0,0],[0,0,0,0,16,130,130,130,130,130,130,130,16,1627389956,16,66,66,66,66,66,66,66,66,66,66,66,16,0,0,0,0],[0,0,0,0,16,130,130,130,838860930,130,130,130,16,4,16,66,66,66,66,66,822083650,66,66,66,66,66,16,0,0,0,0],[0,4,4,4,131076,130,130,130,130,130,130,130,16,4,262148,66,66,66,66,66,66,66,66,66,66,66,16,0,0,0,0],[0,0,0,0,16,130,130,130,130,130,130,130,16,4,16,66,66,66,66,66,66,66,66,66,66,66,16,0,0,0,0],[0,0,0,0,16,130,130,130,130,130,130,130,16,4,16,66,66,66,66,66,66,66,66,66,66,66,16,0,0,0,0],[0,0,0,0,16,16,16,16,16,16,16,16,16,4,16,66,66,66,66,66,66,66,66,66,66,66,16,0,0,0,0],[0,0,0,0,0,4,4,4,4,4,0,0,0,4,16,66,66,66,66,66,66,66,66,66,66,66,16,0,0,0,0],[0,0,0,0,0,4,0,0,0,4,0,0,0,4,16,16,16,65540,16,16,16,262148,16,16,16,16,16,0,0,0,0],[0,0,0,0,0,4,0,4,0,4,0,0,0,4,4,4,0,4,0,4,4,4,4,4,4,4,0,0,0,0,0],[0,0,0,0,0,4,0,4,0,4,0,0,0,0,0,4,0,4,0,4,0,4,0,0,0,4,0,0,0,0,0],[0,0,0,0,0,4,0,4,4,4,4,4,4,4,4,4,0,4,0,4,0,4,0,4194308,0,4,0,0,0,0,0],[0,0,0,0,0,4,0,0,0,0,0,0,0,0,0,0,0,4,0,0,0,4,0,4,0,4,0,0,0,0,0],[0,0,0,0,0,4,4,4,4,4,4,4,4,4,4,4,4,4,4,4,4,4,0,4,4,4,0,0,0,0,0],[0,0,0,0,0,0,0,0,0,0,0,0,0,0,0,0,0,0,0,0,0,0,0,0,0,0,0,0,0,0,0],[0,0,0,0,0,0,0,0,0,0,0,0,0,0,0,0,0,0,0,0,0,0,0,0,0,0,0,0,0,0,0],[0,0,0,0,0,0,0,0,0,0,0,0,0,0,0,0,0,0,0,0,0,0,0,0,0,0,0,0,0,0,0],[0,0,0,0,0,0,0,0,0,0,0,0,0,0,0,0,0,0,0,0,0,0,0,0,0,0,0,0,0,0,0],[0,0,0,0,0,0,0,0,0,0,0,0,0,0,0,0,0,0,0,0,0,0,0,0,0,0,0,0,0,0,0]],"corridor_features":{"a":{"detail":"Earthmaw Trap: DC 15 to find, DC 15 to disable;\n    +8 to hit against one target, 2d10 piercing damage","key":"a","marks":[{"col":13,"row":13}],"summary":"Earthmaw Trap"}},"details":{"floor":"Natural Stone (difficult terrain, disadvantage on acrobatics) (Slippery Foor)","history":"The dungeon was created by yuan-ti as a stronghold. It was eventually conquered by invaders, and has fallen to ruin and been rebuilt many times since then.","illumination":"Average (shadowy in corridors, lamps or torches in most rooms)","special":null,"temperature":"Warm","walls":"Reinforced Masonry (DC 15 to climb)"},"egress":[{"col":1,"depth":0,"dir":"west","room_id":2,"row":11,"type":"room"}],"rooms":[null,{"area":12100,"col":11,"contents":{"detail":{"monster":["2 x Goblin (cr 1/4, mm 166) and 4 x Giant Rat (cr 1/8, mm 327); deadly, 200 xp","--","Treasure: 1700 cp, 1300 sp, 60 gp, diamond (50 gp), chalcedony (50 gp), 2 x moonstone (50 gp), star rose quartz (50 gp), zircon (50 gp), Potion of Greater Healing (uncommon, dmg 187), Potion of Growth (uncommon, dmg 187)"],"room_features":"A mural of arcane patterns covers the ceiling, and a stream of oil flows into the room through a hole in the ceiling","trap":["Teleporter Crystal: DC 15 to find, DC 15 to disable;\n    affects each creature which touches the crystal, DC 10 save or be teleported to another location"]},"inhabited":"2 x Goblin and 4 x Giant Rat","summary":"2 x Goblin and 4 x Giant Rat, Teleporter Crystal"},"doors":{"north":[{"col":13,"desc":"Archway","row":4,"type":"arch"}],"south":[{"col":13,"desc":"Archway","row":16,"type":"arch"},{"col":17,"desc":"Locked Iron Door (DC 15 to open, DC 30 to break; 60 hp)","row":16,"type":"locked"}],"west":[{"col":10,"desc":"Locked Good Wooden Door (DC 15 to open, DC 15 to break; 15 hp)","row":11,"type":"locked"}]},"east":21,"height":110,"id":1,"north":5,"row":5,"shape":"circle","size":"gargantuan","south":15,"west":11,"width":110},{"area":4900,"col":1,"contents":{"detail":{"room_features":"An iron chandelier hangs from the ceiling in the north-west corner of the room, and a rusted iron box lies in the east side of the room"},"summary":"Empty"},"doors":{"east":[{"col":8,"desc":"Unlocked Simple Wooden Door (10 hp)","row":7,"type":"door"}],"west":[{"col":0,"desc":"Stuck Good Wooden Door (DC 15 to break; 15 hp)","row":11,"type":"door"}]},"east":7,"height":70,"id":2,"north":7,"row":7,"shape":"square","size":"medium","south":13,"west":1,"width":70}],"settings":{"add_stairs":"Yes","bleed":4,"cell_size":18,"corridor_layout":"Straight","door_set":"Secure","dungeon_layout":"Square","dungeon_size":"Fine","grid":"Square","image_size":"","infest":"dnd_5e","last_room_id":2,"level":1,"map_cols":"51","map_rows":"65","map_style":"Standard","max_col":22,"max_row":22,"motif":"","n_cols":23,"n_i":11,"n_j":11,"n_pc":4,"n_rooms":2,"n_rows":23,"name":"The Sanctum of the Lich Princess","peripheral_egress":"Yes","remove_arcs":"All","remove_deadends":"Some","room_layout":"Sparse","room_polymorph":"Many","room_size":"Gargantuan","seed":1181828470},"stairs":[{"col":19,"dir":"south","key":"down","row":19},{"col":11,"dir":"east","key":"up","row":3}],"wandering_monsters":{"1":"Orog (cr 2, mm 247); deadly, 450 xp, tracking the party","2":"2 x Hobgoblin (cr 1/2, mm 186); hard, 200 xp, gathered around an evil shrine","3":"Silver Dragon Wyrmling (cr 2, mm 118); deadly, 450 xp, wielding bizarre eldritch powers","4":"Silver Dragon Wyrmling (cr 2, mm 118); deadly, 450 xp, bloodied and fleeing a more powerful enemy","5":"Orc (cr 1/2, mm 246) and 1 x Half-ogre (cr 1, mm 238); deadly, 300 xp, tracking the party","6":"2 x Goblin (cr 1/4, mm 166); easy, 100 xp, scouting from another part of the dungeon"}}